resistors/__init__.py
resistors/main.py
resistors/version.py
resistors/resources/EIA_96_codes.csv
resistors/resources/EIA_96_mul.csv
resistors/resources/__init__.py
resistor_codes-0.0.1.dist-info/LICENSE.txt
resistor_codes-0.0.1.dist-info/METADATA
resistor_codes-0.0.1.dist-info/WHEEL
resistor_codes-0.0.1.dist-info/entry_points.txt
resistor_codes-0.0.1.dist-info/top_level.txt
resistor_codes-0.0.1.dist-info/RECORD
